dist
env
iBook
